[1,["e5xvWUXexK2LgpJPu/MExs"],0,[["sp.SkeletonData",["_name","_atlasText","textureNames","_skeletonJson","textures"],-1,3]],[[0,0,1,2,3,4,5]],[[0,"eff_cleansmoke2","\neff_cleansmoke2.png\nsize: 1009,418\nformat: RGBA8888\nfilter: Linear,Linear\nrepeat: none\neff_cleansmoke_00\n  rotate: false\n  xy: 2, 12\n  size: 240, 206\n  orig: 272, 212\n  offset: 7, 6\n  index: -1\neff_cleansmoke_01\n  rotate: false\n  xy: 275, 215\n  size: 250, 201\n  orig: 272, 212\n  offset: 4, 9\n  index: -1\neff_cleansmoke_02\n  rotate: false\n  xy: 527, 213\n  size: 259, 203\n  orig: 272, 212\n  offset: 2, 6\n  index: -1\neff_cleansmoke_03\n  rotate: false\n  xy: 244, 6\n  size: 265, 207\n  orig: 272, 212\n  offset: 1, 0\n  index: -1\neff_cleansmoke_04\n  rotate: false\n  xy: 2, 220\n  size: 271, 196\n  orig: 272, 212\n  offset: 1, 1\n  index: -1\neff_cleansmoke_05\n  rotate: false\n  xy: 788, 212\n  size: 219, 204\n  orig: 272, 212\n  offset: 30, 1\n  index: -1\neff_cleansmoke_06\n  rotate: false\n  xy: 511, 4\n  size: 234, 207\n  orig: 272, 212\n  offset: 20, 2\n  index: -1\neff_cleansmoke_07\n  rotate: false\n  xy: 747, 2\n  size: 243, 208\n  orig: 272, 212\n  offset: 13, 3\n  index: -1\n",["eff_cleansmoke2.png"],{"skeleton":{"hash":"i1UD1Uno0U8/1P23GOcdU8QMo+c","spine":"3.8.99","images":"./images/","audio":""},"bones":[{"name":"root"},{"name":"eff_cleansmoke_00","parent":"root"}],"slots":[{"name":"eff_cleansmoke_00","bone":"eff_cleansmoke_00"}],"skins":[{"name":"default","attachments":{"eff_cleansmoke_00":{"eff_cleansmoke_00":{"width":272,"height":212},"eff_cleansmoke_01":{"x":0.5,"y":0.5,"width":272,"height":212},"eff_cleansmoke_02":{"x":0.5,"y":0.5,"width":272,"height":212},"eff_cleansmoke_03":{"x":0.5,"y":0.5,"width":272,"height":212},"eff_cleansmoke_04":{"x":0.5,"y":0.5,"width":272,"height":212},"eff_cleansmoke_05":{"x":0.5,"y":0.5,"width":272,"height":212},"eff_cleansmoke_06":{"x":0.5,"y":0.5,"width":272,"height":212},"eff_cleansmoke_07":{"x":0.5,"y":0.5,"width":272,"height":212}}}}],"animations":{"animation":{"slots":{"eff_cleansmoke_00":{"attachment":[{"name":"eff_cleansmoke_00"},{"time":0.0667,"name":"eff_cleansmoke_01"},{"time":0.1333,"name":"eff_cleansmoke_02"},{"time":0.2,"name":"eff_cleansmoke_03"},{"time":0.2667,"name":"eff_cleansmoke_04"},{"time":0.3333,"name":"eff_cleansmoke_05"},{"time":0.4,"name":"eff_cleansmoke_06"},{"time":0.4667,"name":"eff_cleansmoke_07"},{"time":0.5333,"name":"eff_cleansmoke_00"}]}},"bones":{"eff_cleansmoke_00":{"translate":[{"x":-20,"y":21}],"scale":[{"x":2,"y":2}]}}}}},[0]]],0,0,[0],[-1],[0]]